{
  "timestamp": "2025-09-01T08:38:34.096490",
  "data": {
    "sport_id": 1,
    "sport_name": "Soccer",
    "last": 1756683510,
    "last_call": 1756683510,
    "events": [
      {
        "event_id": 1614379455,
        "sport_id": 1,
        "league_id": 1957,
        "league_name": "England - League 1",
        "starts": "2025-09-06T14:00:00",
        "last": 1756682092,
        "home": "Huddersfield Town",
        "away": "Peterborough United",
        "event_type": "prematch",
        "live_status_id": 2,
        "parent_id": null,
        "resulting_unit": "Regular",
        "is_actual": true,
        "home_team_type": "Team1",
        "is_have_odds": true,
        "is_have_periods": true,
        "is_have_open_markets": true,
        "periods": {
          "num_0": {
            "line_id": 3236527918,
            "number": 0,
            "description": "Match",
            "cutoff": "2025-09-06T14:00:00",
            "period_status": 1,
            "money_line": {
              "home": 1.492,
              "draw": 4.39,
              "away": 6.06
            },
            "spreads": {
              "-1.0": {
                "hdp": -1.0,
                "alt_line_id": null,
                "home": 1.826,
                "away": 2.02,
                "max": 300.0
              },
              "-2.0": {
                "hdp": -2.0,
                "alt_line_id": 50506797546,
                "home": 3.75,
                "away": 1.271,
                "max": 300
              },
              "-1.75": {
                "hdp": -1.75,
                "alt_line_id": 50506797548,
                "home": 2.85,
                "away": 1.42,
                "max": 300
              },
              "-1.5": {
                "hdp": -1.5,
                "alt_line_id": 50506797550,
                "home": 2.4,
                "away": 1.578,
                "max": 300
              },
              "-1.25": {
                "hdp": -1.25,
                "alt_line_id": 50506797554,
                "home": 2.11,
                "away": 1.74,
                "max": 300
              },
              "-0.75": {
                "hdp": -0.75,
                "alt_line_id": 50506797558,
                "home": 1.617,
                "away": 2.33,
                "max": 300
              },
              "-0.5": {
                "hdp": -0.5,
                "alt_line_id": 50506797562,
                "home": 1.49,
                "away": 2.64,
                "max": 300
              },
              "-0.25": {
                "hdp": -0.25,
                "alt_line_id": 50506797566,
                "home": 1.332,
                "away": 3.29,
                "max": 300
              },
              "0.0": {
                "hdp": 0.0,
                "alt_line_id": 50506797568,
                "home": 1.184,
                "away": 4.82,
                "max": 300
              }
            },
            "totals": {
              "2.75": {
                "points": 2.75,
                "alt_line_id": null,
                "over": 1.833,
                "under": 1.99,
                "max": 225.0
              },
              "4.5": {
                "points": 4.5,
                "alt_line_id": 50506797547,
                "over": 4.72,
                "under": 1.18,
                "max": 225
              },
              "3.5": {
                "points": 3.5,
                "alt_line_id": 50506797549,
                "over": 2.63,
                "under": 1.473,
                "max": 225
              },
              "3.25": {
                "points": 3.25,
                "alt_line_id": 50506797551,
                "over": 2.37,
                "under": 1.584,
                "max": 225
              },
              "3.0": {
                "points": 3.0,
                "alt_line_id": 50506797555,
                "over": 2.09,
                "under": 1.746,
                "max": 225
              },
              "2.5": {
                "points": 2.5,
                "alt_line_id": 50506797559,
                "over": 1.662,
                "under": 2.22,
                "max": 225
              },
              "2.25": {
                "points": 2.25,
                "alt_line_id": 50506797563,
                "over": 1.48,
                "under": 2.64,
                "max": 225
              },
              "1.5": {
                "points": 1.5,
                "alt_line_id": 50506797567,
                "over": 1.204,
                "under": 4.37,
                "max": 225
              }
            },
            "team_total": {
              "home": {
                "points": 1.5,
                "over": 1.552,
                "under": 2.42
              },
              "away": {
                "points": 0.5,
                "over": 1.564,
                "under": 2.39
              }
            },
            "meta": {
              "number": 0,
              "max_money_line": 300.0,
              "max_spread": 300.0,
              "max_total": 225.0,
              "max_team_total": 100.0,
              "open_money_line": true,
              "open_spreads": true,
              "open_totals": true,
              "open_team_total": true
            }
          },
          "num_1": {
            "line_id": 3236183085,
            "number": 1,
            "description": "1st Half",
            "cutoff": "2025-09-06T14:00:00",
            "period_status": 1,
            "money_line": {
              "home": 1.961,
              "draw": 2.56,
              "away": 6.12
            },
            "spreads": {
              "-0.5": {
                "hdp": -0.5,
                "alt_line_id": null,
                "home": 1.961,
                "away": 1.847,
                "max": 100.0
              },
              "-1.0": {
                "hdp": -1.0,
                "alt_line_id": 50500224189,
                "home": 3.55,
                "away": 1.288,
                "max": 100
              },
              "-0.75": {
                "hdp": -0.75,
                "alt_line_id": 50500224190,
                "home": 2.4,
                "away": 1.561,
                "max": 100
              },
              "-0.25": {
                "hdp": -0.25,
                "alt_line_id": 50500224191,
                "home": 1.591,
                "away": 2.33,
                "max": 100
              },
              "0.0": {
                "hdp": 0.0,
                "alt_line_id": 50500224193,
                "home": 1.24,
                "away": 3.98,
                "max": 100
              }
            },
            "totals": {
              "1.25": {
                "points": 1.25,
                "alt_line_id": null,
                "over": 2.04,
                "under": 1.757,
                "max": 100.0
              },
              "0.75": {
                "points": 0.75,
                "alt_line_id": 50500224200,
                "over": 1.386,
                "under": 2.89,
                "max": 100
              },
              "1.0": {
                "points": 1.0,
                "alt_line_id": 50500224202,
                "over": 1.591,
                "under": 2.29,
                "max": 100
              },
              "1.5": {
                "points": 1.5,
                "alt_line_id": 50500224204,
                "over": 2.46,
                "under": 1.518,
                "max": 100
              },
              "1.75": {
                "points": 1.75,
                "alt_line_id": 50500224206,
                "over": 3.1,
                "under": 1.342,
                "max": 100
              }
            },
            "team_total": {
              "home": {
                "points": 0.5,
                "over": 1.531,
                "under": 2.42
              },
              "away": {
                "points": 0.5,
                "over": 2.92,
                "under": 1.383
              }
            },
            "meta": {
              "number": 1,
              "max_money_line": 100.0,
              "max_spread": 100.0,
              "max_total": 100.0,
              "max_team_total": 100.0,
              "open_money_line": true,
              "open_spreads": true,
              "open_totals": true,
              "open_team_total": true
            }
          }
        }
      },
      {
        "event_id": 1614361225,
        "sport_id": 1,
        "league_id": 1957,
        "league_name": "England - League 1",
        "starts": "2025-09-06T14:00:00",
        "last": 1756682092,
        "home": "Plymouth Argyle",
        "away": "Stockport County",
        "event_type": "prematch",
        "live_status_id": 2,
        "parent_id": null,
        "resulting_unit": "Regular",
        "is_actual": true,
        "home_team_type": "Team1",
        "is_have_odds": true,
        "is_have_periods": true,
        "is_have_open_markets": true,
        "periods": {
          "num_0": {
            "line_id": 3236527626,
            "number": 0,
            "description": "Match",
            "cutoff": "2025-09-06T14:00:00",
            "period_status": 1,
            "money_line": {
              "home": 3.09,
              "draw": 3.5,
              "away": 2.24
            },
            "spreads": {
              "0.25": {
                "hdp": 0.25,
                "alt_line_id": null,
                "home": 1.884,
                "away": 1.952,
                "max": 300.0
              },
              "-0.75": {
                "hdp": -0.75,
                "alt_line_id": 50506792026,
                "home": 3.88,
                "away": 1.257,
                "max": 300
              },
              "-0.5": {
                "hdp": -0.5,
                "alt_line_id": 50506792028,
                "home": 3.07,
                "away": 1.373,
                "max": 300
              },
              "-0.25": {
                "hdp": -0.25,
                "alt_line_id": 50506792030,
                "home": 2.68,
                "away": 1.476,
                "max": 300
              },
              "0.0": {
                "hdp": 0.0,
                "alt_line_id": 50506792034,
                "home": 2.28,
                "away": 1.641,
                "max": 300
              },
              "0.5": {
                "hdp": 0.5,
                "alt_line_id": 50506792038,
                "home": 1.662,
                "away": 2.24,
                "max": 300
              },
              "0.75": {
                "hdp": 0.75,
                "alt_line_id": 50506792042,
                "home": 1.483,
                "away": 2.66,
                "max": 300
              },
              "1.0": {
                "hdp": 1.0,
                "alt_line_id": 50506792046,
                "home": 1.303,
                "away": 3.48,
                "max": 300
              },
              "1.25": {
                "hdp": 1.25,
                "alt_line_id": 50506792048,
                "home": 1.251,
                "away": 3.93,
                "max": 300
              }
            },
            "totals": {
              "2.5": {
                "points": 2.5,
                "alt_line_id": null,
                "over": 1.869,
                "under": 1.952,
                "max": 225.0
              },
              "4.5": {
                "points": 4.5,
                "alt_line_id": 50506792027,
                "over": 5.9,
                "under": 1.126,
                "max": 225
              },
              "3.5": {
                "points": 3.5,
                "alt_line_id": 50506792029,
                "over": 3.14,
                "under": 1.35,
                "max": 225
              },
              "3.0": {
                "points": 3.0,
                "alt_line_id": 50506792031,
                "over": 2.51,
                "under": 1.526,
                "max": 225
              },
              "2.75": {
                "points": 2.75,
                "alt_line_id": 50506792035,
                "over": 2.1,
                "under": 1.735,
                "max": 225
              },
              "2.25": {
                "points": 2.25,
                "alt_line_id": 50506792039,
                "over": 1.641,
                "under": 2.26,
                "max": 225
              },
              "2.0": {
                "points": 2.0,
                "alt_line_id": 50506792043,
                "over": 1.409,
                "under": 2.89,
                "max": 225
              },
              "1.5": {
                "points": 1.5,
                "alt_line_id": 50506792047,
                "over": 1.263,
                "under": 3.72,
                "max": 225
              }
            },
            "team_total": {
              "home": {
                "points": 1.5,
                "over": 2.72,
                "under": 1.45
              },
              "away": {
                "points": 1.5,
                "over": 2.17,
                "under": 1.68
              }
            },
            "meta": {
              "number": 0,
              "max_money_line": 300.0,
              "max_spread": 300.0,
              "max_total": 225.0,
              "max_team_total": 100.0,
              "open_money_line": true,
              "open_spreads": true,
              "open_totals": true,
              "open_team_total": true
            }
          },
          "num_1": {
            "line_id": 3236223946,
            "number": 1,
            "description": "1st Half",
            "cutoff": "2025-09-06T14:00:00",
            "period_status": 1,
            "money_line": {
              "home": 3.7,
              "draw": 2.27,
              "away": 2.85
            },
            "spreads": {
              "0.0": {
                "hdp": 0.0,
                "alt_line_id": null,
                "home": 2.2,
                "away": 1.675,
                "max": 100.0
              },
              "-0.5": {
                "hdp": -0.5,
                "alt_line_id": 50501061377,
                "home": 3.67,
                "away": 1.273,
                "max": 100
              },
              "-0.25": {
                "hdp": -0.25,
                "alt_line_id": 50501061378,
                "home": 2.95,
                "away": 1.393,
                "max": 100
              },
              "0.25": {
                "hdp": 0.25,
                "alt_line_id": 50501061379,
                "home": 1.625,
                "away": 2.26,
                "max": 100
              },
              "0.5": {
                "hdp": 0.5,
                "alt_line_id": 50501061380,
                "home": 1.416,
                "away": 2.83,
                "max": 100
              }
            },
            "totals": {
              "1.0": {
                "points": 1.0,
                "alt_line_id": null,
                "over": 1.775,
                "under": 2.01,
                "max": 100.0
              },
              "0.5": {
                "points": 0.5,
                "alt_line_id": 50501061383,
                "over": 1.344,
                "under": 3.09,
                "max": 100
              },
              "0.75": {
                "points": 0.75,
                "alt_line_id": 50501061384,
                "over": 1.483,
                "under": 2.56,
                "max": 100
              },
              "1.25": {
                "points": 1.25,
                "alt_line_id": 50501061385,
                "over": 2.27,
                "under": 1.598,
                "max": 100
              },
              "1.5": {
                "points": 1.5,
                "alt_line_id": 50501061386,
                "over": 2.75,
                "under": 1.42,
                "max": 100
              }
            },
            "team_total": {
              "home": {
                "points": 0.5,
                "over": 2.24,
                "under": 1.617
              },
              "away": {
                "points": 0.5,
                "over": 1.934,
                "under": 1.826
              }
            },
            "meta": {
              "number": 1,
              "max_money_line": 100.0,
              "max_spread": 100.0,
              "max_total": 100.0,
              "max_team_total": 100.0,
              "open_money_line": true,
              "open_spreads": true,
              "open_totals": true,
              "open_team_total": true
            }
          }
        }
      },
      {
        "event_id": 1614375945,
        "sport_id": 1,
        "league_id": 1957,
        "league_name": "England - League 1",
        "starts": "2025-09-06T14:00:00",
        "last": 1756682092,
        "home": "Bolton Wanderers",
        "away": "AFC Wimbledon",
        "event_type": "prematch",
        "live_status_id": 2,
        "parent_id": null,
        "resulting_unit": "Regular",
        "is_actual": true,
        "home_team_type": "Team1",
        "is_have_odds": true,
        "is_have_periods": true,
        "is_have_open_markets": true,
        "periods": {
          "num_0": {
            "line_id": 3236527855,
            "number": 0,
            "description": "Match",
            "cutoff": "2025-09-06T14:00:00",
            "period_status": 1,
            "money_line": {
              "home": 1.699,
              "draw": 3.67,
              "away": 5.02
            },
            "spreads": {
              "-0.75": {
                "hdp": -0.75,
                "alt_line_id": null,
                "home": 1.917,
                "away": 1.917,
                "max": 300.0
              },
              "-1.75": {
                "hdp": -1.75,
                "alt_line_id": 50506796332,
                "home": 3.76,
                "away": 1.27,
                "max": 300
              },
              "-1.5": {
                "hdp": -1.5,
                "alt_line_id": 50506796334,
                "home": 2.99,
                "away": 1.387,
                "max": 300
              },
              "-1.25": {
                "hdp": -1.25,
                "alt_line_id": 50506796336,
                "home": 2.65,
                "away": 1.487,
                "max": 300
              },
              "-1.0": {
                "hdp": -1.0,
                "alt_line_id": 50506796340,
                "home": 2.28,
                "away": 1.641,
                "max": 300
              },
              "-0.5": {
                "hdp": -0.5,
                "alt_line_id": 50506796344,
                "home": 1.699,
                "away": 2.18,
                "max": 300
              },
              "-0.25": {
                "hdp": -0.25,
                "alt_line_id": 50506796348,
                "home": 1.48,
                "away": 2.66,
                "max": 300
              },
              "0.0": {
                "hdp": 0.0,
                "alt_line_id": 50506796353,
                "home": 1.267,
                "away": 3.78,
                "max": 300
              },
              "0.25": {
                "hdp": 0.25,
                "alt_line_id": 50506796357,
                "home": 1.213,
                "away": 4.37,
                "max": 300
              }
            },
            "totals": {
              "2.25": {
                "points": 2.25,
                "alt_line_id": null,
                "over": 1.847,
                "under": 1.98,
                "max": 225.0
              },
              "3.5": {
                "points": 3.5,
                "alt_line_id": 50506796335,
                "over": 3.7,
                "under": 1.267,
                "max": 225
              },
              "2.75": {
                "points": 2.75,
                "alt_line_id": 50506796337,
                "over": 2.42,
                "under": 1.558,
                "max": 225
              },
              "2.5": {
                "points": 2.5,
                "alt_line_id": 50506796341,
                "over": 2.1,
                "under": 1.735,
                "max": 225
              },
              "2.0": {
                "points": 2.0,
                "alt_line_id": 50506796345,
                "over": 1.568,
                "under": 2.41,
                "max": 225
              },
              "1.75": {
                "points": 1.75,
                "alt_line_id": 50506796349,
                "over": 1.432,
                "under": 2.8,
                "max": 225
              },
              "1.5": {
                "points": 1.5,
                "alt_line_id": 50506796355,
                "over": 1.344,
                "under": 3.16,
                "max": 225
              }
            },
            "team_total": {
              "home": {
                "points": 1.5,
                "over": 1.917,
                "under": 1.869
              },
              "away": {
                "points": 0.5,
                "over": 1.675,
                "under": 2.17
              }
            },
            "meta": {
              "number": 0,
              "max_money_line": 300.0,
              "max_spread": 300.0,
              "max_total": 225.0,
              "max_team_total": 100.0,
              "open_money_line": true,
              "open_spreads": true,
              "open_totals": true,
              "open_team_total": true
            }
          },
          "num_1": {
            "line_id": 3235775679,
            "number": 1,
            "description": "1st Half",
            "cutoff": "2025-09-06T14:00:00",
            "period_status": 1,
            "money_line": {
              "home": 2.28,
              "draw": 2.23,
              "away": 5.7
            },
            "spreads": {
              "-0.25": {
                "hdp": -0.25,
                "alt_line_id": null,
                "home": 1.793,
                "away": 2.02,
                "max": 100.0
              },
              "-0.75": {
                "hdp": -0.75,
                "alt_line_id": 50491871845,
                "home": 2.93,
                "away": 1.392,
                "max": 100
              },
              "-0.5": {
                "hdp": -0.5,
                "alt_line_id": 50491871846,
                "home": 2.27,
                "away": 1.625,
                "max": 100
              },
              "0.0": {
                "hdp": 0.0,
                "alt_line_id": 50491871847,
                "home": 1.312,
                "away": 3.4,
                "max": 100
              },
              "0.25": {
                "hdp": 0.25,
                "alt_line_id": 50491871848,
                "home": 1.196,
                "away": 4.54,
                "max": 100
              }
            },
            "totals": {
              "1.0": {
                "points": 1.0,
                "alt_line_id": null,
                "over": 1.99,
                "under": 1.793,
                "max": 100.0
              },
              "0.5": {
                "points": 0.5,
                "alt_line_id": 50491871855,
                "over": 1.408,
                "under": 2.8,
                "max": 100
              },
              "0.75": {
                "points": 0.75,
                "alt_line_id": 50491871856,
                "over": 1.584,
                "under": 2.3,
                "max": 100
              },
              "1.25": {
                "points": 1.25,
                "alt_line_id": 50491871857,
                "over": 2.55,
                "under": 1.485,
                "max": 100
              },
              "1.5": {
                "points": 1.5,
                "alt_line_id": 50491871858,
                "over": 3.09,
                "under": 1.344,
                "max": 100
              }
            },
            "team_total": {
              "home": {
                "points": 0.5,
                "over": 1.775,
                "under": 1.99
              },
              "away": {
                "points": 0.5,
                "over": 3.13,
                "under": 1.34
              }
            },
            "meta": {
              "number": 1,
              "max_money_line": 100.0,
              "max_spread": 100.0,
              "max_total": 100.0,
              "max_team_total": 100.0,
              "open_money_line": true,
              "open_spreads": true,
              "open_totals": true,
              "open_team_total": true
            }
          }
        }
      },
      {
        "event_id": 1614375944,
        "sport_id": 1,
        "league_id": 1957,
        "league_name": "England - League 1",
        "starts": "2025-09-06T14:00:00",
        "last": 1756682092,
        "home": "Port Vale",
        "away": "Leyton Orient",
        "event_type": "prematch",
        "live_status_id": 2,
        "parent_id": null,
        "resulting_unit": "Regular",
        "is_actual": true,
        "home_team_type": "Team1",
        "is_have_odds": true,
        "is_have_periods": true,
        "is_have_open_markets": true,
        "periods": {
          "num_0": {
            "line_id": 3236527617,
            "number": 0,
            "description": "Match",
            "cutoff": "2025-09-06T14:00:00",
            "period_status": 1,
            "money_line": {
              "home": 2.28,
              "draw": 3.65,
              "away": 2.92
            },
            "spreads": {
              "-0.25": {
                "hdp": -0.25,
                "alt_line_id": null,
                "home": 2.0,
                "away": 1.847,
                "max": 300.0
              },
              "-1.25": {
                "hdp": -1.25,
                "alt_line_id": 50506791822,
                "home": 4.08,
                "away": 1.237,
                "max": 300
              },
              "-1.0": {
                "hdp": -1.0,
                "alt_line_id": 50506791824,
                "home": 3.61,
                "away": 1.286,
                "max": 300
              },
              "-0.75": {
                "hdp": -0.75,
                "alt_line_id": 50506791826,
                "home": 2.72,
                "away": 1.462,
                "max": 300
              },
              "-0.5": {
                "hdp": -0.5,
                "alt_line_id": 50506791830,
                "home": 2.28,
                "away": 1.641,
                "max": 300
              },
              "0.0": {
                "hdp": 0.0,
                "alt_line_id": 50506791834,
                "home": 1.694,
                "away": 2.18,
                "max": 300
              },
              "0.25": {
                "hdp": 0.25,
                "alt_line_id": 50506791838,
                "home": 1.52,
                "away": 2.55,
                "max": 300
              },
              "0.5": {
                "hdp": 0.5,
                "alt_line_id": 50506791842,
                "home": 1.409,
                "away": 2.9,
                "max": 300
              },
              "0.75": {
                "hdp": 0.75,
                "alt_line_id": 50506791844,
                "home": 1.278,
                "away": 3.68,
                "max": 300
              }
            },
            "totals": {
              "2.25": {
                "points": 2.25,
                "alt_line_id": null,
                "over": 1.806,
                "under": 2.02,
                "max": 225.0
              },
              "3.5": {
                "points": 3.5,
                "alt_line_id": 50506791825,
                "over": 3.69,
                "under": 1.268,
                "max": 225
              },
              "2.75": {
                "points": 2.75,
                "alt_line_id": 50506791827,
                "over": 2.37,
                "under": 1.581,
                "max": 225
              },
              "2.5": {
                "points": 2.5,
                "alt_line_id": 50506791831,
                "over": 2.06,
                "under": 1.769,
                "max": 225
              },
              "2.0": {
                "points": 2.0,
                "alt_line_id": 50506791835,
                "over": 1.543,
                "under": 2.47,
                "max": 225
              },
              "1.75": {
                "points": 1.75,
                "alt_line_id": 50506791839,
                "over": 1.418,
                "under": 2.86,
                "max": 225
              },
              "1.5": {
                "points": 1.5,
                "alt_line_id": 50506791843,
                "over": 1.334,
                "under": 3.23,
                "max": 225
              }
            },
            "team_total": {
              "home": {
                "points": 1.5,
                "over": 2.4,
                "under": 1.558
              },
              "away": {
                "points": 1.5,
                "over": 2.96,
                "under": 1.39
              }
            },
            "meta": {
              "number": 0,
              "max_money_line": 300.0,
              "max_spread": 300.0,
              "max_total": 225.0,
              "max_team_total": 100.0,
              "open_money_line": true,
              "open_spreads": true,
              "open_totals": true,
              "open_team_total": true
            }
          },
          "num_1": {
            "line_id": 3236222869,
            "number": 1,
            "description": "1st Half",
            "cutoff": "2025-09-06T14:00:00",
            "period_status": 1,
            "money_line": {
              "home": 2.98,
              "draw": 2.17,
              "away": 3.78
            },
            "spreads": {
              "0.0": {
                "hdp": 0.0,
                "alt_line_id": null,
                "home": 1.689,
                "away": 2.17,
                "max": 100.0
              },
              "-0.5": {
                "hdp": -0.5,
                "alt_line_id": 50501039533,
                "home": 2.95,
                "away": 1.387,
                "max": 100
              },
              "-0.25": {
                "hdp": -0.25,
                "alt_line_id": 50501039534,
                "home": 2.33,
                "away": 1.591,
                "max": 100
              },
              "0.25": {
                "hdp": 0.25,
                "alt_line_id": 50501039535,
                "home": 1.387,
                "away": 2.98,
                "max": 100
              },
              "0.5": {
                "hdp": 0.5,
                "alt_line_id": 50501039536,
                "home": 1.264,
                "away": 3.75,
                "max": 100
              }
            },
            "totals": {
              "1.0": {
                "points": 1.0,
                "alt_line_id": null,
                "over": 1.952,
                "under": 1.819,
                "max": 100.0
              },
              "0.5": {
                "points": 0.5,
                "alt_line_id": 50501039539,
                "over": 1.398,
                "under": 2.83,
                "max": 100
              },
              "0.75": {
                "points": 0.75,
                "alt_line_id": 50501039540,
                "over": 1.568,
                "under": 2.33,
                "max": 100
              },
              "1.25": {
                "points": 1.25,
                "alt_line_id": 50501039541,
                "over": 2.5,
                "under": 1.502,
                "max": 100
              },
              "1.5": {
                "points": 1.5,
                "alt_line_id": 50501039542,
                "over": 3.03,
                "under": 1.355,
                "max": 100
              }
            },
            "team_total": {
              "home": {
                "points": 0.5,
                "over": 2.04,
                "under": 1.735
              },
              "away": {
                "points": 0.5,
                "over": 2.36,
                "under": 1.555
              }
            },
            "meta": {
              "number": 1,
              "max_money_line": 100.0,
              "max_spread": 100.0,
              "max_total": 100.0,
              "max_team_total": 100.0,
              "open_money_line": true,
              "open_spreads": true,
              "open_totals": true,
              "open_team_total": true
            }
          }
        }
      },
      {
        "event_id": 1614361228,
        "sport_id": 1,
        "league_id": 1957,
        "league_name": "England - League 1",
        "starts": "2025-09-06T14:00:00",
        "last": 1756682092,
        "home": "Wycombe Wanderers",
        "away": "Mansfield Town",
        "event_type": "prematch",
        "live_status_id": 2,
        "parent_id": null,
        "resulting_unit": "Regular",
        "is_actual": true,
        "home_team_type": "Team1",
        "is_have_odds": true,
        "is_have_periods": true,
        "is_have_open_markets": true,
        "periods": {
          "num_0": {
            "line_id": 3236528881,
            "number": 0,
            "description": "Match",
            "cutoff": "2025-09-06T14:00:00",
            "period_status": 1,
            "money_line": {
              "home": 2.07,
              "draw": 3.58,
              "away": 3.42
            },
            "spreads": {
              "-0.25": {
                "hdp": -0.25,
                "alt_line_id": null,
                "home": 1.8,
                "away": 2.05,
                "max": 300.0
              },
              "-1.25": {
                "hdp": -1.25,
                "alt_line_id": 50506813322,
                "home": 3.45,
                "away": 1.293,
                "max": 300
              },
              "-1.0": {
                "hdp": -1.0,
                "alt_line_id": 50506813324,
                "home": 3.04,
                "away": 1.362,
                "max": 300
              },
              "-0.75": {
                "hdp": -0.75,
                "alt_line_id": 50506813326,
                "home": 2.39,
                "away": 1.561,
                "max": 300
              },
              "-0.5": {
                "hdp": -0.5,
                "alt_line_id": 50506813330,
                "home": 2.05,
                "away": 1.763,
                "max": 300
              },
              "0.0": {
                "hdp": 0.0,
                "alt_line_id": 50506813334,
                "home": 1.512,
                "away": 2.53,
                "max": 300
              },
              "0.25": {
                "hdp": 0.25,
                "alt_line_id": 50506813338,
                "home": 1.389,
                "away": 2.95,
                "max": 300
              },
              "0.5": {
                "hdp": 0.5,
                "alt_line_id": 50506813342,
                "home": 1.307,
                "away": 3.35,
                "max": 300
              },
              "0.75": {
                "hdp": 0.75,
                "alt_line_id": 50506813344,
                "home": 1.206,
                "away": 4.3,
                "max": 300
              }
            },
            "totals": {
              "2.5": {
                "points": 2.5,
                "alt_line_id": null,
                "over": 1.961,
                "under": 1.862,
                "max": 225.0
              },
              "4.5": {
                "points": 4.5,
                "alt_line_id": 50506813323,
                "over": 6.29,
                "under": 1.104,
                "max": 225
              },
              "3.5": {
                "points": 3.5,
                "alt_line_id": 50506813325,
                "over": 3.3,
                "under": 1.305,
                "max": 225
              },
              "3.0": {
                "points": 3.0,
                "alt_line_id": 50506813327,
                "over": 2.67,
                "under": 1.452,
                "max": 225
              },
              "2.75": {
                "points": 2.75,
                "alt_line_id": 50506813331,
                "over": 2.2,
                "under": 1.649,
                "max": 225
              },
              "2.25": {
                "points": 2.25,
                "alt_line_id": 50506813335,
                "over": 1.699,
                "under": 2.12,
                "max": 225
              },
              "2.0": {
                "points": 2.0,
                "alt_line_id": 50506813339,
                "over": 1.46,
                "under": 2.64,
                "max": 225
              },
              "1.5": {
                "points": 1.5,
                "alt_line_id": 50506813343,
                "over": 1.289,
                "under": 3.41,
                "max": 225
              }
            },
            "team_total": {
              "home": {
                "points": 1.5,
                "over": 2.13,
                "under": 1.709
              },
              "away": {
                "points": 0.5,
                "over": 1.406,
                "under": 2.82
              }
            },
            "meta": {
              "number": 0,
              "max_money_line": 300.0,
              "max_spread": 300.0,
              "max_total": 225.0,
              "max_team_total": 100.0,
              "open_money_line": true,
              "open_spreads": true,
              "open_totals": true,
              "open_team_total": true
            }
          },
          "num_1": {
            "line_id": 3235721231,
            "number": 1,
            "description": "1st Half",
            "cutoff": "2025-09-06T14:00:00",
            "period_status": 1,
            "money_line": {
              "home": 2.7,
              "draw": 2.24,
              "away": 4.13
            },
            "spreads": {
              "-0.25": {
                "hdp": -0.25,
                "alt_line_id": null,
                "home": 2.13,
                "away": 1.719,
                "max": 100.0
              },
              "-0.75": {
                "hdp": -0.75,
                "alt_line_id": 50490734674,
                "home": 3.54,
                "away": 1.274,
                "max": 100
              },
              "-0.5": {
                "hdp": -0.5,
                "alt_line_id": 50490734676,
                "home": 2.65,
                "away": 1.452,
                "max": 100
              },
              "0.0": {
                "hdp": 0.0,
                "alt_line_id": 50490734678,
                "home": 1.54,
                "away": 2.4,
                "max": 100
              },
              "0.25": {
                "hdp": 0.25,
                "alt_line_id": 50490734680,
                "home": 1.318,
                "away": 3.23,
                "max": 100
              }
            },
            "totals": {
              "1.0": {
                "points": 1.0,
                "alt_line_id": null,
                "over": 1.854,
                "under": 1.917,
                "max": 100.0
              },
              "0.5": {
                "points": 0.5,
                "alt_line_id": 50490734675,
                "over": 1.359,
                "under": 2.94,
                "max": 100
              },
              "0.75": {
                "points": 0.75,
                "alt_line_id": 50490734677,
                "over": 1.51,
                "under": 2.43,
                "max": 100
              },
              "1.25": {
                "points": 1.25,
                "alt_line_id": 50490734679,
                "over": 2.35,
                "under": 1.537,
                "max": 100
              },
              "1.5": {
                "points": 1.5,
                "alt_line_id": 50490734681,
                "over": 2.85,
                "under": 1.377,
                "max": 100
              }
            },
            "team_total": {
              "home": {
                "points": 0.5,
                "over": 1.9,
                "under": 1.854
              },
              "away": {
                "points": 0.5,
                "over": 2.42,
                "under": 1.51
              }
            },
            "meta": {
              "number": 1,
              "max_money_line": 100.0,
              "max_spread": 100.0,
              "max_total": 100.0,
              "max_team_total": 100.0,
              "open_money_line": true,
              "open_spreads": true,
              "open_totals": true,
              "open_team_total": true
            }
          }
        }
      },
      {
        "event_id": 1614375948,
        "sport_id": 1,
        "league_id": 1957,
        "league_name": "England - League 1",
        "starts": "2025-09-06T14:00:00",
        "last": 1756682092,
        "home": "Lincoln City",
        "away": "Wigan Athletic",
        "event_type": "prematch",
        "live_status_id": 2,
        "parent_id": null,
        "resulting_unit": "Regular",
        "is_actual": true,
        "home_team_type": "Team1",
        "is_have_odds": true,
        "is_have_periods": true,
        "is_have_open_markets": true,
        "periods": {
          "num_0": {
            "line_id": 3236528040,
            "number": 0,
            "description": "Match",
            "cutoff": "2025-09-06T14:00:00",
            "period_status": 1,
            "money_line": {
              "home": 2.34,
              "draw": 3.08,
              "away": 3.29
            },
            "spreads": {
              "-0.25": {
                "hdp": -0.25,
                "alt_line_id": null,
                "home": 1.99,
                "away": 1.847,
                "max": 300.0
              },
              "-1.25": {
                "hdp": -1.25,
                "alt_line_id": 50506799998,
                "home": 4.58,
                "away": 1.199,
                "max": 300
              },
              "-1.0": {
                "hdp": -1.0,
                "alt_line_id": 50506800000,
                "home": 4.02,
                "away": 1.242,
                "max": 300
              },
              "-0.75": {
                "hdp": -0.75,
                "alt_line_id": 50506800002,
                "home": 2.87,
                "away": 1.425,
                "max": 300
              },
              "-0.5": {
                "hdp": -0.5,
                "alt_line_id": 50506800006,
                "home": 2.34,
                "away": 1.609,
                "max": 300
              },
              "0.0": {
                "hdp": 0.0,
                "alt_line_id": 50506800010,
                "home": 1.625,
                "away": 2.31,
                "max": 300
              },
              "0.25": {
                "hdp": 0.25,
                "alt_line_id": 50506800014,
                "home": 1.442,
                "away": 2.8,
                "max": 300
              },
              "0.5": {
                "hdp": 0.5,
                "alt_line_id": 50506800018,
                "home": 1.336,
                "away": 3.27,
                "max": 300
              },
              "0.75": {
                "hdp": 0.75,
                "alt_line_id": 50506800020,
                "home": 1.22,
                "away": 4.29,
                "max": 300
              }
            },
            "totals": {
              "2.0": {
                "points": 2.0,
                "alt_line_id": null,
                "over": 1.961,
                "under": 1.854,
                "max": 225.0
              },
              "3.5": {
                "points": 3.5,
                "alt_line_id": 50506800001,
                "over": 5.21,
                "under": 1.154,
                "max": 225
              },
              "2.5": {
                "points": 2.5,
                "alt_line_id": 50506800003,
                "over": 2.64,
                "under": 1.478,
                "max": 225
              },
              "2.25": {
                "points": 2.25,
                "alt_line_id": 50506800007,
                "over": 2.31,
                "under": 1.617,
                "max": 225
              },
              "1.75": {
                "points": 1.75,
                "alt_line_id": 50506800011,
                "over": 1.684,
                "under": 2.19,
                "max": 225
              },
              "1.5": {
                "points": 1.5,
                "alt_line_id": 50506800015,
                "over": 1.526,
                "under": 2.51,
                "max": 225
              },
              "0.5": {
                "points": 0.5,
                "alt_line_id": 50506800019,
                "over": 1.108,
                "under": 6.52,
                "max": 225
              }
            },
            "team_total": {
              "home": {
                "points": 1.5,
                "over": 2.89,
                "under": 1.406
              },
              "away": {
                "points": 0.5,
                "over": 1.552,
                "under": 2.42
              }
            },
            "meta": {
              "number": 0,
              "max_money_line": 300.0,
              "max_spread": 300.0,
              "max_total": 225.0,
              "max_team_total": 100.0,
              "open_money_line": true,
              "open_spreads": true,
              "open_totals": true,
              "open_team_total": true
            }
          },
          "num_1": {
            "line_id": 3236223368,
            "number": 1,
            "description": "1st Half",
            "cutoff": "2025-09-06T14:00:00",
            "period_status": 1,
            "money_line": {
              "home": 3.16,
              "draw": 1.961,
              "away": 4.23
            },
            "spreads": {
              "0.0": {
                "hdp": 0.0,
                "alt_line_id": null,
                "home": 1.649,
                "away": 2.25,
                "max": 100.0
              },
              "-0.5": {
                "hdp": -0.5,
                "alt_line_id": 50501049686,
                "home": 3.13,
                "away": 1.352,
                "max": 100
              },
              "-0.25": {
                "hdp": -0.25,
                "alt_line_id": 50501049688,
                "home": 2.4,
                "away": 1.558,
                "max": 100
              },
              "0.25": {
                "hdp": 0.25,
                "alt_line_id": 50501049690,
                "home": 1.336,
                "away": 3.24,
                "max": 100
              },
              "0.5": {
                "hdp": 0.5,
                "alt_line_id": 50501049692,
                "home": 1.222,
                "away": 4.19,
                "max": 100
              }
            },
            "totals": {
              "0.75": {
                "points": 0.75,
                "alt_line_id": null,
                "over": 1.826,
                "under": 1.952,
                "max": 100.0
              },
              "0.5": {
                "points": 0.5,
                "alt_line_id": 50501049696,
                "over": 1.552,
                "under": 2.37,
                "max": 100
              },
              "1.0": {
                "points": 1.0,
                "alt_line_id": 50501049697,
                "over": 2.48,
                "under": 1.507,
                "max": 100
              },
              "1.25": {
                "points": 1.25,
                "alt_line_id": 50501049698,
                "over": 3.16,
                "under": 1.331,
                "max": 100
              }
            },
            "team_total": {
              "home": {
                "points": 0.5,
                "over": 2.29,
                "under": 1.588
              },
              "away": {
                "points": 0.5,
                "over": 2.78,
                "under": 1.416
              }
            },
            "meta": {
              "number": 1,
              "max_money_line": 100.0,
              "max_spread": 100.0,
              "max_total": 100.0,
              "max_team_total": 100.0,
              "open_money_line": true,
              "open_spreads": true,
              "open_totals": true,
              "open_team_total": true
            }
          }
        }
      },
      {
        "event_id": 1614361233,
        "sport_id": 1,
        "league_id": 1957,
        "league_name": "England - League 1",
        "starts": "2025-09-06T14:00:00",
        "last": 1756682092,
        "home": "Doncaster Rovers",
        "away": "Bradford City",
        "event_type": "prematch",
        "live_status_id": 2,
        "parent_id": null,
        "resulting_unit": "Regular",
        "is_actual": true,
        "home_team_type": "Team1",
        "is_have_odds": true,
        "is_have_periods": true,
        "is_have_open_markets": true,
        "periods": {
          "num_0": {
            "line_id": 3237777318,
            "number": 0,
            "description": "Match",
            "cutoff": "2025-09-06T14:00:00",
            "period_status": 1,
            "money_line": {
              "home": 2.3,
              "draw": 3.33,
              "away": 3.14
            },
            "spreads": {
              "-0.25": {
                "hdp": -0.25,
                "alt_line_id": null,
                "home": 1.98,
                "away": 1.854,
                "max": 300.0
              },
              "-1.25": {
                "hdp": -1.25,
                "alt_line_id": 50530206663,
                "home": 4.13,
                "away": 1.233,
                "max": 300
              },
              "-1.0": {
                "hdp": -1.0,
                "alt_line_id": 50530206664,
                "home": 3.66,
                "away": 1.28,
                "max": 300
              },
              "-0.75": {
                "hdp": -0.75,
                "alt_line_id": 50530206665,
                "home": 2.75,
                "away": 1.456,
                "max": 300
              },
              "-0.5": {
                "hdp": -0.5,
                "alt_line_id": 50530206666,
                "home": 2.3,
                "away": 1.632,
                "max": 300
              },
              "0.0": {
                "hdp": 0.0,
                "alt_line_id": 50530206667,
                "home": 1.649,
                "away": 2.27,
                "max": 300
              },
              "0.25": {
                "hdp": 0.25,
                "alt_line_id": 50530206668,
                "home": 1.471,
                "away": 2.7,
                "max": 300
              },
              "0.5": {
                "hdp": 0.5,
                "alt_line_id": 50530206669,
                "home": 1.363,
                "away": 3.11,
                "max": 300
              },
              "0.75": {
                "hdp": 0.75,
                "alt_line_id": 50530206670,
                "home": 1.248,
                "away": 3.97,
                "max": 300
              }
            },
            "totals": {
              "2.5": {
                "points": 2.5,
                "alt_line_id": null,
                "over": 2.02,
                "under": 1.813,
                "max": 225.0
              },
              "4.5": {
                "points": 4.5,
                "alt_line_id": 50530206689,
                "over": 6.85,
                "under": 1.1,
                "max": 225
              },
              "3.5": {
                "points": 3.5,
                "alt_line_id": 50530206692,
                "over": 3.51,
                "under": 1.291,
                "max": 225
              },
              "3.0": {
                "points": 3.0,
                "alt_line_id": 50530206696,
                "over": 2.83,
                "under": 1.425,
                "max": 225
              },
              "2.75": {
                "points": 2.75,
                "alt_line_id": 50530206700,
                "over": 2.31,
                "under": 1.617,
                "max": 225
              },
              "2.25": {
                "points": 2.25,
                "alt_line_id": 50530206703,
                "over": 1.757,
                "under": 2.07,
                "max": 225
              },
              "2.0": {
                "points": 2.0,
                "alt_line_id": 50530206706,
                "over": 1.497,
                "under": 2.59,
                "max": 225
              },
              "1.5": {
                "points": 1.5,
                "alt_line_id": 50530206708,
                "over": 1.305,
                "under": 3.4,
                "max": 225
              }
            },
            "team_total": {
              "home": {
                "points": 1.5,
                "over": 2.32,
                "under": 1.598
              },
              "away": {
                "points": 1.5,
                "over": 2.92,
                "under": 1.398
              }
            },
            "meta": {
              "number": 0,
              "max_money_line": 300.0,
              "max_spread": 300.0,
              "max_total": 225.0,
              "max_team_total": 100.0,
              "open_money_line": true,
              "open_spreads": true,
              "open_totals": true,
              "open_team_total": true
            }
          },
          "num_1": {
            "line_id": 3237777319,
            "number": 1,
            "description": "1st Half",
            "cutoff": "2025-09-06T14:00:00",
            "period_status": 1,
            "money_line": {
              "home": 2.92,
              "draw": 2.2,
              "away": 3.79
            },
            "spreads": {
              "0.0": {
                "hdp": 0.0,
                "alt_line_id": null,
                "home": 1.675,
                "away": 2.2,
                "max": 100.0
              },
              "-0.5": {
                "hdp": -0.5,
                "alt_line_id": 50530206678,
                "home": 2.9,
                "away": 1.4,
                "max": 100
              },
              "-0.25": {
                "hdp": -0.25,
                "alt_line_id": 50530206680,
                "home": 2.3,
                "away": 1.609,
                "max": 100
              },
              "0.25": {
                "hdp": 0.25,
                "alt_line_id": 50530206682,
                "home": 1.384,
                "away": 2.99,
                "max": 100
              },
              "0.5": {
                "hdp": 0.5,
                "alt_line_id": 50530206684,
                "home": 1.263,
                "away": 3.75,
                "max": 100
              }
            },
            "totals": {
              "1.0": {
                "points": 1.0,
                "alt_line_id": null,
                "over": 1.9,
                "under": 1.869,
                "max": 100.0
              },
              "0.5": {
                "points": 0.5,
                "alt_line_id": 50530206698,
                "over": 1.383,
                "under": 2.9,
                "max": 100
              },
              "0.75": {
                "points": 0.75,
                "alt_line_id": 50530206701,
                "over": 1.543,
                "under": 2.39,
                "max": 100
              },
              "1.25": {
                "points": 1.25,
                "alt_line_id": 50530206704,
                "over": 2.44,
                "under": 1.526,
                "max": 100
              },
              "1.5": {
                "points": 1.5,
                "alt_line_id": 50530206707,
                "over": 2.95,
                "under": 1.371,
                "max": 100
              }
            },
            "team_total": {
              "home": {
                "points": 0.5,
                "over": 2.0,
                "under": 1.763
              },
              "away": {
                "points": 0.5,
                "over": 2.34,
                "under": 1.564
              }
            },
            "meta": {
              "number": 1,
              "max_money_line": 100.0,
              "max_spread": 100.0,
              "max_total": 100.0,
              "max_team_total": 100.0,
              "open_money_line": true,
              "open_spreads": true,
              "open_totals": true,
              "open_team_total": true
            }
          }
        }
      },
      {
        "event_id": 1614379462,
        "sport_id": 1,
        "league_id": 1957,
        "league_name": "England - League 1",
        "starts": "2025-09-06T14:00:00",
        "last": 1756682092,
        "home": "Rotherham United",
        "away": "Exeter City",
        "event_type": "prematch",
        "live_status_id": 2,
        "parent_id": null,
        "resulting_unit": "Regular",
        "is_actual": true,
        "home_team_type": "Team1",
        "is_have_odds": true,
        "is_have_periods": true,
        "is_have_open_markets": true,
        "periods": {
          "num_0": {
            "line_id": 3236529551,
            "number": 0,
            "description": "Match",
            "cutoff": "2025-09-06T14:00:00",
            "period_status": 1,
            "money_line": {
              "home": 2.23,
              "draw": 3.32,
              "away": 3.27
            },
            "spreads": {
              "-0.25": {
                "hdp": -0.25,
                "alt_line_id": null,
                "home": 1.925,
                "away": 1.909,
                "max": 300.0
              },
              "-1.25": {
                "hdp": -1.25,
                "alt_line_id": 50506823834,
                "home": 4.0,
                "away": 1.245,
                "max": 300
              },
              "-1.0": {
                "hdp": -1.0,
                "alt_line_id": 50506823836,
                "home": 3.53,
                "away": 1.297,
                "max": 300
              },
              "-0.75": {
                "hdp": -0.75,
                "alt_line_id": 50506823838,
                "home": 2.66,
                "away": 1.483,
                "max": 300
              },
              "-0.5": {
                "hdp": -0.5,
                "alt_line_id": 50506823842,
                "home": 2.23,
                "away": 1.666,
                "max": 300
              },
              "0.0": {
                "hdp": 0.0,
                "alt_line_id": 50506823846,
                "home": 1.598,
                "away": 2.37,
                "max": 300
              },
              "0.25": {
                "hdp": 0.25,
                "alt_line_id": 50506823850,
                "home": 1.438,
                "away": 2.82,
                "max": 300
              },
              "0.5": {
                "hdp": 0.5,
                "alt_line_id": 50506823854,
                "home": 1.34,
                "away": 3.24,
                "max": 300
              },
              "0.75": {
                "hdp": 0.75,
                "alt_line_id": 50506823856,
                "home": 1.23,
                "away": 4.17,
                "max": 300
              }
            },
            "totals": {
              "2.25": {
                "points": 2.25,
                "alt_line_id": null,
                "over": 1.806,
                "under": 2.03,
                "max": 225.0
              },
              "3.5": {
                "points": 3.5,
                "alt_line_id": 50506823837,
                "over": 3.6,
                "under": 1.278,
                "max": 225
              },
              "2.75": {
                "points": 2.75,
                "alt_line_id": 50506823839,
                "over": 2.36,
                "under": 1.584,
                "max": 225
              },
              "2.5": {
                "points": 2.5,
                "alt_line_id": 50506823843,
                "over": 2.06,
                "under": 1.769,
                "max": 225
              },
              "2.0": {
                "points": 2.0,
                "alt_line_id": 50506823847,
                "over": 1.531,
                "under": 2.5,
                "max": 225
              },
              "1.75": {
                "points": 1.75,
                "alt_line_id": 50506823851,
                "over": 1.406,
                "under": 2.91,
                "max": 225
              },
              "1.5": {
                "points": 1.5,
                "alt_line_id": 50506823855,
                "over": 1.323,
                "under": 3.29,
                "max": 225
              }
            },
            "team_total": {
              "home": {
                "points": 1.5,
                "over": 2.32,
                "under": 1.598
              },
              "away": {
                "points": 0.5,
                "over": 1.401,
                "under": 2.91
              }
            },
            "meta": {
              "number": 0,
              "max_money_line": 300.0,
              "max_spread": 300.0,
              "max_total": 225.0,
              "max_team_total": 100.0,
              "open_money_line": true,
              "open_spreads": true,
              "open_totals": true,
              "open_team_total": true
            }
          },
          "num_1": {
            "line_id": 3236518732,
            "number": 1,
            "description": "1st Half",
            "cutoff": "2025-09-06T14:00:00",
            "period_status": 1,
            "money_line": {
              "home": 2.86,
              "draw": 2.18,
              "away": 3.94
            },
            "spreads": {
              "-0.25": {
                "hdp": -0.25,
                "alt_line_id": null,
                "home": 2.25,
                "away": 1.645,
                "max": 100.0
              },
              "-0.75": {
                "hdp": -0.75,
                "alt_line_id": 50506643601,
                "home": 3.87,
                "away": 1.25,
                "max": 100
              },
              "-0.5": {
                "hdp": -0.5,
                "alt_line_id": 50506643602,
                "home": 2.85,
                "away": 1.416,
                "max": 100
              },
              "0.0": {
                "hdp": 0.0,
                "alt_line_id": 50506643603,
                "home": 1.621,
                "away": 2.27,
                "max": 100
              },
              "0.25": {
                "hdp": 0.25,
                "alt_line_id": 50506643605,
                "home": 1.357,
                "away": 3.1,
                "max": 100
              }
            },
            "totals": {
              "1.0": {
                "points": 1.0,
                "alt_line_id": null,
                "over": 1.943,
                "under": 1.833,
                "max": 100.0
              },
              "0.5": {
                "points": 0.5,
                "alt_line_id": 50506643615,
                "over": 1.395,
                "under": 2.85,
                "max": 100
              },
              "0.75": {
                "points": 0.75,
                "alt_line_id": 50506643616,
                "over": 1.561,
                "under": 2.35,
                "max": 100
              },
              "1.25": {
                "points": 1.25,
                "alt_line_id": 50506643617,
                "over": 2.49,
                "under": 1.507,
                "max": 100
              },
              "1.5": {
                "points": 1.5,
                "alt_line_id": 50506643618,
                "over": 3.01,
                "under": 1.359,
                "max": 100
              }
            },
            "team_total": {
              "home": {
                "points": 0.5,
                "over": 2.0,
                "under": 1.769
              },
              "away": {
                "points": 0.5,
                "over": 2.42,
                "under": 1.531
              }
            },
            "meta": {
              "number": 1,
              "max_money_line": 100.0,
              "max_spread": 100.0,
              "max_total": 100.0,
              "max_team_total": 100.0,
              "open_money_line": true,
              "open_spreads": true,
              "open_totals": true,
              "open_team_total": true
            }
          }
        }
      }
    ]
  }
}