{
  "timestamp": "2025-09-01T08:28:46.441928",
  "data": {
    "sport_id": 3,
    "sport_name": "Basketball",
    "last": 1756682880,
    "last_call": 1756682923,
    "events": [
      {
        "event_id": 1614326804,
        "sport_id": 3,
        "league_id": 578,
        "league_name": "WNBA",
        "starts": "2025-09-01T00:00:00",
        "last": 1756682604,
        "home": "Los Angeles Sparks",
        "away": "Washington Mystics",
        "event_type": "prematch",
        "live_status_id": 2,
        "parent_id": null,
        "resulting_unit": "Regular",
        "is_actual": true,
        "home_team_type": "Team2",
        "is_have_odds": true,
        "is_have_periods": true,
        "is_have_open_markets": true,
        "periods": {
          "num_0": {
            "line_id": 3238151554,
            "number": 0,
            "description": "Game",
            "cutoff": "2025-09-01T00:00:00",
            "period_status": 1,
            "money_line": {
              "home": 1.245,
              "draw": null,
              "away": 4.26
            },
            "spreads": {
              "-9.0": {
                "hdp": -9.0,
                "alt_line_id": null,
                "home": 1.943,
                "away": 1.909,
                "max": 3000.0
              },
              "-7.5": {
                "hdp": -7.5,
                "alt_line_id": 50537824790,
                "home": 1.719,
                "away": 2.14,
                "max": 3000
              },
              "-8.0": {
                "hdp": -8.0,
                "alt_line_id": 50537824791,
                "home": 1.781,
                "away": 2.06,
                "max": 3000
              },
              "-8.5": {
                "hdp": -8.5,
                "alt_line_id": 50537824792,
                "home": 1.847,
                "away": 1.97,
                "max": 3000
              },
              "-9.5": {
                "hdp": -9.5,
                "alt_line_id": 50537824793,
                "home": 2.01,
                "away": 1.813,
                "max": 3000
              },
              "-10.0": {
                "hdp": -10.0,
                "alt_line_id": 50537824794,
                "home": 2.1,
                "away": 1.746,
                "max": 3000
              },
              "-10.5": {
                "hdp": -10.5,
                "alt_line_id": 50537824795,
                "home": 2.19,
                "away": 1.694,
                "max": 3000
              }
            },
            "totals": {
              "168.5": {
                "points": 168.5,
                "alt_line_id": null,
                "over": 1.917,
                "under": 1.934,
                "max": 2000.0
              },
              "167.0": {
                "points": 167.0,
                "alt_line_id": 50537824800,
                "over": 1.769,
                "under": 2.07,
                "max": 2000
              },
              "167.5": {
                "points": 167.5,
                "alt_line_id": 50537824801,
                "over": 1.806,
                "under": 2.02,
                "max": 2000
              },
              "168.0": {
                "points": 168.0,
                "alt_line_id": 50537824802,
                "over": 1.854,
                "under": 1.97,
                "max": 2000
              },
              "169.0": {
                "points": 169.0,
                "alt_line_id": 50537824803,
                "over": 1.952,
                "under": 1.862,
                "max": 2000
              },
              "169.5": {
                "points": 169.5,
                "alt_line_id": 50537824804,
                "over": 2.01,
                "under": 1.813,
                "max": 2000
              },
              "170.0": {
                "points": 170.0,
                "alt_line_id": 50537824805,
                "over": 2.09,
                "under": 1.757,
                "max": 2000
              }
            },
            "team_total": {
              "home": {
                "points": 88.0,
                "over": 1.869,
                "under": 1.952
              },
              "away": {
                "points": 79.5,
                "over": 1.925,
                "under": 1.892
              }
            },
            "meta": {
              "number": 0,
              "max_money_line": 2000.0,
              "max_spread": 3000.0,
              "max_total": 2000.0,
              "max_team_total": 500.0,
              "open_money_line": true,
              "open_spreads": true,
              "open_totals": true,
              "open_team_total": true
            }
          },
          "num_1": {
            "line_id": 3238165417,
            "number": 1,
            "description": "1st Half",
            "cutoff": "2025-09-01T00:00:00",
            "period_status": 1,
            "money_line": null,
            "spreads": {
              "-5.0": {
                "hdp": -5.0,
                "alt_line_id": null,
                "home": 1.9,
                "away": 1.917,
                "max": 1000.0
              },
              "-4.0": {
                "hdp": -4.0,
                "alt_line_id": 50538099327,
                "home": 1.68,
                "away": 2.16,
                "max": 1000
              },
              "-4.5": {
                "hdp": -4.5,
                "alt_line_id": 50538099328,
                "home": 1.769,
                "away": 2.03,
                "max": 1000
              },
              "-5.5": {
                "hdp": -5.5,
                "alt_line_id": 50538099329,
                "home": 2.01,
                "away": 1.787,
                "max": 1000
              },
              "-6.0": {
                "hdp": -6.0,
                "alt_line_id": 50538099330,
                "home": 2.14,
                "away": 1.694,
                "max": 1000
              }
            },
            "totals": {
              "82.5": {
                "points": 82.5,
                "alt_line_id": null,
                "over": 1.943,
                "under": 1.877,
                "max": 500.0
              },
              "81.5": {
                "points": 81.5,
                "alt_line_id": 50538099347,
                "over": 1.781,
                "under": 2.02,
                "max": 500
              },
              "82.0": {
                "points": 82.0,
                "alt_line_id": 50538099348,
                "over": 1.847,
                "under": 1.934,
                "max": 500
              },
              "83.0": {
                "points": 83.0,
                "alt_line_id": 50538099349,
                "over": 2.05,
                "under": 1.763,
                "max": 500
              },
              "83.5": {
                "points": 83.5,
                "alt_line_id": 50538099350,
                "over": 2.16,
                "under": 1.684,
                "max": 500
              }
            },
            "team_total": null,
            "meta": {
              "number": 1,
              "max_money_line": 500.0,
              "max_spread": 1000.0,
              "max_total": 500.0,
              "open_money_line": false,
              "open_spreads": true,
              "open_totals": true,
              "open_team_total": false
            }
          }
        }
      },
      {
        "event_id": 1614324089,
        "sport_id": 3,
        "league_id": 578,
        "league_name": "WNBA",
        "starts": "2025-09-01T00:30:00",
        "last": 1756682592,
        "home": "Golden State Valkyries",
        "away": "Indiana Fever",
        "event_type": "prematch",
        "live_status_id": 2,
        "parent_id": null,
        "resulting_unit": "Regular",
        "is_actual": true,
        "home_team_type": "Team2",
        "is_have_odds": true,
        "is_have_periods": true,
        "is_have_open_markets": true,
        "periods": {
          "num_0": {
            "line_id": 3238165221,
            "number": 0,
            "description": "Game",
            "cutoff": "2025-09-01T00:30:00",
            "period_status": 1,
            "money_line": {
              "home": 2.21,
              "draw": null,
              "away": 1.704
            },
            "spreads": {
              "2.5": {
                "hdp": 2.5,
                "alt_line_id": null,
                "home": 1.961,
                "away": 1.892,
                "max": 5000.0
              },
              "4.0": {
                "hdp": 4.0,
                "alt_line_id": 50538095746,
                "home": 1.735,
                "away": 2.12,
                "max": 5000
              },
              "3.5": {
                "hdp": 3.5,
                "alt_line_id": 50538095747,
                "home": 1.793,
                "away": 2.04,
                "max": 5000
              },
              "3.0": {
                "hdp": 3.0,
                "alt_line_id": 50538095748,
                "home": 1.862,
                "away": 1.961,
                "max": 5000
              },
              "2.0": {
                "hdp": 2.0,
                "alt_line_id": 50538095749,
                "home": 2.02,
                "away": 1.806,
                "max": 5000
              },
              "1.5": {
                "hdp": 1.5,
                "alt_line_id": 50538095750,
                "home": 2.1,
                "away": 1.746,
                "max": 5000
              },
              "1.0": {
                "hdp": 1.0,
                "alt_line_id": 50538095751,
                "home": 2.16,
                "away": 1.709,
                "max": 5000
              }
            },
            "totals": {
              "159.0": {
                "points": 159.0,
                "alt_line_id": null,
                "over": 1.869,
                "under": 1.99,
                "max": 3000.0
              },
              "157.5": {
                "points": 157.5,
                "alt_line_id": 50538095756,
                "over": 1.714,
                "under": 2.15,
                "max": 3000
              },
              "158.0": {
                "points": 158.0,
                "alt_line_id": 50538095757,
                "over": 1.757,
                "under": 2.09,
                "max": 3000
              },
              "158.5": {
                "points": 158.5,
                "alt_line_id": 50538095758,
                "over": 1.806,
                "under": 2.02,
                "max": 3000
              },
              "159.5": {
                "points": 159.5,
                "alt_line_id": 50538095759,
                "over": 1.9,
                "under": 1.917,
                "max": 3000
              },
              "160.0": {
                "points": 160.0,
                "alt_line_id": 50538095760,
                "over": 1.952,
                "under": 1.862,
                "max": 3000
              },
              "160.5": {
                "points": 160.5,
                "alt_line_id": 50538095761,
                "over": 2.01,
                "under": 1.819,
                "max": 3000
              }
            },
            "team_total": {
              "home": {
                "points": 78.0,
                "over": 1.877,
                "under": 1.934
              },
              "away": {
                "points": 80.5,
                "over": 1.884,
                "under": 1.934
              }
            },
            "meta": {
              "number": 0,
              "max_money_line": 3000.0,
              "max_spread": 5000.0,
              "max_total": 3000.0,
              "max_team_total": 500.0,
              "open_money_line": true,
              "open_spreads": true,
              "open_totals": true,
              "open_team_total": true
            }
          },
          "num_1": {
            "line_id": 3238161083,
            "number": 1,
            "description": "1st Half",
            "cutoff": "2025-09-01T00:30:00",
            "period_status": 1,
            "money_line": {
              "home": 2.15,
              "draw": null,
              "away": 1.714
            },
            "spreads": {
              "1.0": {
                "hdp": 1.0,
                "alt_line_id": null,
                "home": 1.934,
                "away": 1.884,
                "max": 1000.0
              },
              "2.0": {
                "hdp": 2.0,
                "alt_line_id": 50538014459,
                "home": 1.735,
                "away": 2.08,
                "max": 1000
              },
              "1.5": {
                "hdp": 1.5,
                "alt_line_id": 50538014460,
                "home": 1.819,
                "away": 1.97,
                "max": 1000
              },
              "0.5": {
                "hdp": 0.5,
                "alt_line_id": 50538014461,
                "home": 2.02,
                "away": 1.781,
                "max": 1000
              },
              "0.0": {
                "hdp": 0.0,
                "alt_line_id": 50538014462,
                "home": 2.13,
                "away": 1.699,
                "max": 1000
              }
            },
            "totals": {
              "82.0": {
                "points": 82.0,
                "alt_line_id": null,
                "over": 1.961,
                "under": 1.862,
                "max": 500.0
              },
              "81.0": {
                "points": 81.0,
                "alt_line_id": 50538014469,
                "over": 1.8,
                "under": 1.99,
                "max": 500
              },
              "81.5": {
                "points": 81.5,
                "alt_line_id": 50538014470,
                "over": 1.869,
                "under": 1.917,
                "max": 500
              },
              "82.5": {
                "points": 82.5,
                "alt_line_id": 50538014471,
                "over": 2.01,
                "under": 1.787,
                "max": 500
              },
              "83.0": {
                "points": 83.0,
                "alt_line_id": 50538014472,
                "over": 2.08,
                "under": 1.735,
                "max": 500
              }
            },
            "team_total": null,
            "meta": {
              "number": 1,
              "max_money_line": 1000.0,
              "max_spread": 1000.0,
              "max_total": 500.0,
              "open_money_line": true,
              "open_spreads": true,
              "open_totals": true,
              "open_team_total": false
            }
          }
        }
      }
    ]
  }
}